plesicdb/__about__.py
plesicdb/__init__.py
plesicdb/_base.py
plesicdb/_collection.py
plesicdb/_database.py
plesicdb/_helpers.py
plesicdb/_utils.py
PlesicDB-1.0.2.dist-info/METADATA
PlesicDB-1.0.2.dist-info/WHEEL
PlesicDB-1.0.2.dist-info/top_level.txt
PlesicDB-1.0.2.dist-info/RECORD
