Metadata-Version: 2.1
Name: PlesicDB
Version: 1.0.2
Summary: Document(JSON) oriented database
Home-page: https://github.com/hakiKhuva/plesicdb
Author: Harkishan Khuva
Author-email: harkishankhuva02@gmail.com
License: MIT
Platform: UNKNOWN
Classifier: Programming Language :: Python :: 3
Requires-Python: >=3.6
